{
  "cypress": {
    "firstname": "Admin",
    "lastname": "Cypress",
    "mail": "admin@cypress.kummer",
    "password": "OriginalPassword1!",
    "id": "123456"
  },
  "admin": {
    "firstname": "Admin",
    "lastname": "Kummerkasten",
    "mail": "admin@kummer.kasten",
    "password": "admin"
  },
  "fsles1": {
    "firstname": "Fachschaft",
    "lastname": "Eins",
    "mail": "fsles1@kummerkasten.local",
    "password": "fachschaft"
  },
  "chef": {
    "firstname": "Chef",
    "lastname": "Fe",
    "mail": "cheffe@kummerkasten.local",
    "password": "cheffe"
  },
  "temp": {
    "firstname": "Test",
    "lastname": "User",
    "mail": "test.user@kummer.kasten",
    "password": "EinTestPasswort123!"
  }
}
